libcreator/__init__.py
libcreator/__main__.py
libcreator/libcreator.py
libcreator-0.1.2.dist-info/METADATA
libcreator-0.1.2.dist-info/WHEEL
libcreator-0.1.2.dist-info/top_level.txt
libcreator-0.1.2.dist-info/RECORD
