Metadata-Version: 2.1
Name: libcreator
Version: 0.1.2
Summary: A python library to create new libraries
Home-page: UNKNOWN
Author: Luca Grosshennig
Author-email: luca.grosshennig@gmx.de
License: MIT
Platform: UNKNOWN
Classifier: Intended Audience :: Developers
Classifier: License :: OSI Approved :: MIT License
Classifier: Programming Language :: Python
Classifier: Programming Language :: Python :: 3
Classifier: Programming Language :: Python :: 3.6
Classifier: Programming Language :: Python :: 3.7
Classifier: Programming Language :: Python :: 3.8
Classifier: Programming Language :: Python :: 3.9
Classifier: Operating System :: OS Independent
Requires-Dist: wheel
Requires-Dist: twine
